cubicweb_addressbook/__init__.py
cubicweb_addressbook/__pkginfo__.py
cubicweb_addressbook/entities.py
cubicweb_addressbook/hooks.py
cubicweb_addressbook/schema.py
cubicweb_addressbook/views.py
cubicweb_addressbook/i18n/en.po
cubicweb_addressbook/i18n/es.po
cubicweb_addressbook/i18n/fr.po
cubicweb_addressbook/migration/1.13.2_Any.py
cubicweb_addressbook/migration/1.2.1_Any.py
cubicweb_addressbook/migration/1.2.4_Any.py
cubicweb_addressbook/migration/1.5.0_Any.py
cubicweb_addressbook/migration/1.6.2_Any.py
cubicweb_addressbook/migration/1.6.3_Any.py
cubicweb_addressbook/migration/postcreate.py
cubicweb_addressbook/schema/_regproc.postgres.sql
cubicweb_addressbook-2.2.1.dist-info/METADATA
cubicweb_addressbook-2.2.1.dist-info/WHEEL
cubicweb_addressbook-2.2.1.dist-info/entry_points.txt
cubicweb_addressbook-2.2.1.dist-info/top_level.txt
cubicweb_addressbook-2.2.1.dist-info/RECORD
