Metadata-Version: 2.4
Name: cubicweb-addressbook
Version: 2.2.1
Summary: address book component for the CubicWeb framework
Home-page: https://forge.extranet.logilab.fr/cubicweb/cubes/cubicweb-addressbook
Author: Logilab
Author-email: contact@logilab.fr
License: LGPL
Classifier: Environment :: Web Environment
Classifier: Framework :: CubicWeb
Classifier: Programming Language :: Python
Classifier: Programming Language :: Python :: 3
Classifier: Programming Language :: Python :: 3 :: Only
Classifier: Programming Language :: JavaScript
Requires-Python: >=3.9.2
Requires-Dist: cubicweb<6.0.0,>=4.5.3
Requires-Dist: cubicweb-web<2.0.0,>=1.4.2
Requires-Dist: cubicweb-geocoding<2.0.0,>=1.0.0
Dynamic: author
Dynamic: author-email
Dynamic: classifier
Dynamic: description
Dynamic: home-page
Dynamic: license
Dynamic: requires-dist
Dynamic: requires-python
Dynamic: summary
